tkMetronomeApp/MetronomeApp.py
tkMetronomeApp/__init__.py
tkMetronomeApp/exceptions.py
tkMetronomeApp/metronome.py
tkMetronomeApp/tkMetronomeViewManager.py
tkmetronomeapp-1.0.0.data/data/Help/tkMetronomeApp/MetronomeApp_HelpFile.txt
tkmetronomeapp-1.0.0.dist-info/METADATA
tkmetronomeapp-1.0.0.dist-info/WHEEL
tkmetronomeapp-1.0.0.dist-info/entry_points.txt
tkmetronomeapp-1.0.0.dist-info/licenses/LICENSE
tkmetronomeapp-1.0.0.dist-info/RECORD
