Metadata-Version: 2.4
Name: tkMetronomeApp
Version: 1.0.0
Summary: tkMetronomeApp is a python package that provides a tkinter based metronome application for musicians.
Keywords: query,console,input,response
Author-Email: "Kevin R. Geurts" <kevin.r.geurts@gmail.com>
License-Expression: MIT
License-File: LICENSE
Classifier: Programming Language :: Python :: 3
Classifier: Operating System :: OS Independent
Classifier: Development Status :: 5 - Production/Stable
Classifier: Environment :: Win32 (MS Windows)
Classifier: Environment :: X11 Applications
Classifier: Intended Audience :: End Users/Desktop
Classifier: Topic :: Artistic Software
Project-URL: Homepage, https://github.com/KevinRGeurts/tkMetronomeApp
Project-URL: Issues, https://github.com/KevinRGeurts/tkMetronomeApp/issues
Requires-Python: >=3.12
Requires-Dist: tkAppFramework>=0.9.0
